aurornis/__init__.py
aurornis/model.py
aurornis-1.6.0.dist-info/LICENSE.md
aurornis-1.6.0.dist-info/METADATA
aurornis-1.6.0.dist-info/WHEEL
aurornis-1.6.0.dist-info/RECORD
