Metadata-Version: 2.3
Name: aurornis
Version: 1.6.0
Summary: A command line program test helper
License: AGPL-3.0-or-later
Author: Jérôme Deuchnord
Author-email: jerome@deuchnord.fr
Requires-Python: >=3.7,<4.0
Classifier: Development Status :: 5 - Production/Stable
Classifier: Intended Audience :: Developers
Classifier: License :: OSI Approved :: GNU Affero General Public License v3 or later (AGPLv3+)
Classifier: Programming Language :: Python :: 3
Classifier: Programming Language :: Python :: 3.7
Classifier: Programming Language :: Python :: 3.8
Classifier: Programming Language :: Python :: 3.9
Classifier: Programming Language :: Python :: 3.10
Classifier: Programming Language :: Python :: 3.11
Classifier: Programming Language :: Python :: 3.12
Classifier: Programming Language :: Python :: 3.13
Classifier: Topic :: Software Development :: Libraries :: Python Modules
Classifier: Topic :: Software Development :: Testing
Requires-Dist: deprecation (>=2.1.0,<3.0.0)
Project-URL: Repository, https://github.com/Deuchnord/Aurornis
